sftplib/__init__.py
sftplib/exceptions.py
sftplib/ftp.py
sftplib/sftp.py
sftplib-0.0.2.dist-info/LICENSE
sftplib-0.0.2.dist-info/METADATA
sftplib-0.0.2.dist-info/WHEEL
sftplib-0.0.2.dist-info/top_level.txt
sftplib-0.0.2.dist-info/RECORD
