Metadata-Version: 2.1
Name: sftplib
Version: 0.0.2
Summary: A very simple S/FTP client python package
Author: AP Consulting S.r.l.
Author-email: areasviluppo@apconsulting.net
Maintainer-email: Filippo Veneri <filippo.veneri@apconsulting.net>
License: MIT License        
Project-URL: homepage, https://github.com/apconsulting/sftplib
Project-URL: repository, https://github.com/apconsulting/sftplib
Keywords: sftp,ftp
Classifier: Development Status :: 3 - Alpha
Classifier: Programming Language :: Python
Requires-Python: >=3.7
License-File: LICENSE
Requires-Dist: paramiko (>=2.7.1)
